MANIFEST.in
README.md
pyproject.toml
setup.py
amuse_bse.egg-info/PKG-INFO
amuse_bse.egg-info/SOURCES.txt
amuse_bse.egg-info/dependency_links.txt
amuse_bse.egg-info/requires.txt
amuse_bse.egg-info/top_level.txt
src/amuse/community/bse/Makefile
src/amuse/community/bse/README
src/amuse/community/bse/__init__.py
src/amuse/community/bse/_version.py
src/amuse/community/bse/interface.f
src/amuse/community/bse/interface.py
src/amuse/community/bse/src/Makefile
src/amuse/community/bse/src/README_BSE
src/amuse/community/bse/src/README_SSE
src/amuse/community/bse/src/binaries.in
src/amuse/community/bse/src/binary.in
src/amuse/community/bse/src/bse.f
src/amuse/community/bse/src/comenv.f
src/amuse/community/bse/src/const_bse.h
src/amuse/community/bse/src/corerd.f
src/amuse/community/bse/src/deltat.f
src/amuse/community/bse/src/dgcore.f
src/amuse/community/bse/src/evolv1.f
src/amuse/community/bse/src/evolv2.f
src/amuse/community/bse/src/evolve.in
src/amuse/community/bse/src/gntage.f
src/amuse/community/bse/src/hrdiag.f
src/amuse/community/bse/src/instar.f
src/amuse/community/bse/src/kick.f
src/amuse/community/bse/src/mix.f
src/amuse/community/bse/src/mlwind.f
src/amuse/community/bse/src/mrenv.f
src/amuse/community/bse/src/popbin.f
src/amuse/community/bse/src/ran3.f
src/amuse/community/bse/src/rl.f
src/amuse/community/bse/src/sse.f
src/amuse/community/bse/src/star.f
src/amuse/community/bse/src/zcnsts.f
src/amuse/community/bse/src/zdata.h
src/amuse/community/bse/src/zfuncs.f
support/__init__.py
support/classifiers.py
support/config.py
support/generate_main.py
support/getsp.class
support/getsp.java
support/misc.py
support/setup_codes.py
support/version.py